titan/__init__.py
titan/__main__.py
titan/cli.py
titan/jwt.py
titan/mq.py
titan/sms.py
titan/utils.py
titan/web.py
titan/templates/.dockerignore
titan/templates/.gitignore
titan/templates/Dockerfile
titan/templates/README.md
titan/templates/docker-compoe.yml
titan/templates/gunicorn_config.py
titan/templates/requirements.txt
titan/templates/wsgi.py
titan/templates/app/__init__.py
titan/templates/app/callbacks.py
titan/templates/app/routes.py
titan/templates/config/__init__.py
titan/templates/config/development.py
titan/templates/config/production.py
titan/templates/config/testing.py
titan/templates/tests/__init__.py
titan/templates/tests/test_api.py
titan/templates/tests/utils.py
pytitan-1.0.14.dist-info/METADATA
pytitan-1.0.14.dist-info/WHEEL
pytitan-1.0.14.dist-info/entry_points.txt
pytitan-1.0.14.dist-info/top_level.txt
pytitan-1.0.14.dist-info/RECORD
